b5/__init__.py
b5/exceptions.py
b5/execute.py
b5/init.py
b5/main.py
b5/bash/default_tasks.sh
b5/bash/functions.sh
b5/bash/init.sh
b5/lib/__init__.py
b5/lib/argumentparser.py
b5/lib/config.py
b5/lib/detect.py
b5/lib/importutils.py
b5/lib/module.py
b5/lib/script.py
b5/lib/skeleton.py
b5/lib/state.py
b5/lib/taskfile.py
b5/lib/version.py
b5/modules/__init__.py
b5/modules/comlipy.py
b5/modules/composer.py
b5/modules/docker.py
b5/modules/npm.py
b5/modules/pipenv.py
b5/modules/template.py
b5/modules/test.py
b5/modules/virtualenv.py
b5/tests/lib/test_argumentparser.py
b5-1.5.2.dist-info/METADATA
b5-1.5.2.dist-info/WHEEL
b5-1.5.2.dist-info/entry_points.txt
b5-1.5.2.dist-info/licenses/LICENSE
b5-1.5.2.dist-info/RECORD
