Metadata-Version: 2.4
Name: b5
Version: 1.5.2
Summary: b5 - simple and sane task runner
Project-URL: Homepage, https://github.com/team23/b5
Project-URL: Repository, https://github.com/team23/b5
Project-URL: Documentation, https://github.com/team23/b5/tree/master/docs
Author-email: David Danier <danier@team23.de>
License-Expression: MIT
License-File: LICENSE
Classifier: Development Status :: 5 - Production/Stable
Classifier: Environment :: Console
Classifier: Intended Audience :: Developers
Classifier: Intended Audience :: System Administrators
Classifier: Operating System :: MacOS :: MacOS X
Classifier: Operating System :: POSIX
Classifier: Operating System :: POSIX :: Linux
Classifier: Operating System :: Unix
Classifier: Programming Language :: Python
Classifier: Programming Language :: Python :: 3 :: Only
Classifier: Programming Language :: Python :: 3.10
Classifier: Programming Language :: Python :: 3.11
Classifier: Programming Language :: Python :: 3.12
Classifier: Programming Language :: Python :: 3.13
Classifier: Topic :: Software Development
Classifier: Topic :: Software Development :: Build Tools
Classifier: Topic :: System :: Systems Administration
Requires-Python: >=3.10
Requires-Dist: jinja2<4.0,>=3.1
Requires-Dist: markupsafe<4.0,>=3.0
Requires-Dist: packaging>=24.0
Requires-Dist: pyyaml<7.0,>=6.0
Requires-Dist: termcolor<4.0,>=3.1
